trytond/modules/account_aged_balance_defaults/README.rst
trytond/modules/account_aged_balance_defaults/__init__.py
trytond/modules/account_aged_balance_defaults/account.py
trytond/modules/account_aged_balance_defaults/configuration.py
trytond/modules/account_aged_balance_defaults/configuration.xml
trytond/modules/account_aged_balance_defaults/tryton.cfg
trytond/modules/account_aged_balance_defaults/versiondep.txt
trytond/modules/account_aged_balance_defaults/locale/de.po
trytond/modules/account_aged_balance_defaults/locale/en.po
trytond/modules/account_aged_balance_defaults/view/configuration_form.xml
mds_account_aged_balance_defaults-5.0.0.dist-info/METADATA
mds_account_aged_balance_defaults-5.0.0.dist-info/WHEEL
mds_account_aged_balance_defaults-5.0.0.dist-info/entry_points.txt
mds_account_aged_balance_defaults-5.0.0.dist-info/top_level.txt
mds_account_aged_balance_defaults-5.0.0.dist-info/RECORD
