Metadata-Version: 2.1
Name: mds-account-aged-balance-defaults
Version: 5.0.0
Summary: Tryton module to add defaults to the aged-balance-sheet in accounting.
Home-page: https://www.m-ds.de/
Author: m-ds
Author-email: service@m-ds.de
License: GPL-3
Keywords: tryton account defaults settings
Platform: UNKNOWN
Classifier: Development Status :: 5 - Production/Stable
Classifier: Environment :: Plugins
Classifier: Framework :: Tryton
Classifier: Intended Audience :: Developers
Classifier: Intended Audience :: Customer Service
Classifier: Intended Audience :: Information Technology
Classifier: Topic :: Office/Business
Classifier: Natural Language :: German
Classifier: Natural Language :: English
Classifier: Operating System :: OS Independent
Classifier: License :: OSI Approved :: GNU General Public License (GPL)
Classifier: Programming Language :: Python :: 3.4
Classifier: Programming Language :: Python :: 3.5
Classifier: Programming Language :: Python :: 3.6
Requires-Dist: trytond-account (<5.1,>=5.0)
Requires-Dist: trytond (<5.1,>=5.0)
